[
{"id": 0, "paragraphs": [{"raw": "King Hassan II l-\u1e25asan a\u1e6f-\u1e6f\u0101n\u012b, also known as l-\u1e25asan ett \u00e2ni, was King of Morocco from 1961 until his death in 1999.\nHe was a member of the Alaouite dynasty.\nHe was the eldest son of Mohammed V, Sultan, then King of Morocco, and his second wife, Lalla Abla bint Tahar.\nHassan was known to be one of the most severe rulers of Morocco, widely accused of authoritarian practices and of being an autocrat and a dictator, particularly during the Years of Lead.\n", "sentences": [{"tokens": [{"id": 0, "orth": "King", "tag": "NNP", "head": 2, "dep": "compound", "ner": "B-PERSON"}, {"id": 1, "orth": "Hassan", "tag": "NNP", "head": 1, "dep": "compound", "ner": "I-PERSON"}, {"id": 2, "orth": "II", "tag": "NNP", "head": 6, "dep": "compound", "ner": "I-PERSON"}, {"id": 3, "orth": "l", "tag": "NNP", "head": 2, "dep": "compound", "ner": "I-PERSON"}, {"id": 4, "orth": "-", "tag": "HYPH", "head": 1, "dep": "punct", "ner": "I-PERSON"}, {"id": 5, "orth": "\u1e25asan", "tag": "JJ", "head": 3, "dep": "compound", "ner": "L-PERSON"}, {"id": 6, "orth": "a\u1e6f", "tag": "NNP", "head": 2, "dep": "compound", "ner": "O"}, {"id": 7, "orth": "-", "tag": "HYPH", "head": 1, "dep": "punct", "ner": "O"}, {"id": 8, "orth": "\u1e6f\u0101n\u012b", "tag": "NNP", "head": 11, "dep": "nsubj", "ner": "O"}, {"id": 9, "orth": ",", "tag": ",", "head": -1, "dep": "punct", "ner": "O"}, {"id": 10, "orth": "also", "tag": "RB", "head": 1, "dep": "advmod", "ner": "O"}, {"id": 11, "orth": "known", "tag": "VBN", "head": -3, "dep": "acl", "ner": "O"}, {"id": 12, "orth": "as", "tag": "IN", "head": -1, "dep": "prep", "ner": "O"}, {"id": 13, "orth": "l", "tag": "NN", "head": 2, "dep": "compound", "ner": "O"}, {"id": 14, "orth": "-", "tag": "HYPH", "head": 1, "dep": "punct", "ner": "O"}, {"id": 15, "orth": "\u1e25asan", "tag": "NNP", "head": 2, "dep": "compound", "ner": "O"}, {"id": 16, "orth": "ett", "tag": "NNP", "head": 1, "dep": "compound", "ner": "O"}, {"id": 17, "orth": "\u00e2ni", "tag": "NNP", "head": -5, "dep": "pobj", "ner": "O"}, {"id": 18, "orth": ",", "tag": ",", "head": 1, "dep": "punct", "ner": "O"}, {"id": 19, "orth": "was", "tag": "VBD", "head": 0, "dep": "ROOT", "ner": "O"}, {"id": 20, "orth": "King", "tag": "NNP", "head": -1, "dep": "attr", "ner": "B-ORG"}, {"id": 21, "orth": "of", "tag": "IN", "head": -1, "dep": "prep", "ner": "I-ORG"}, {"id": 22, "orth": "Morocco", "tag": "NNP", "head": -1, "dep": "pobj", "ner": "L-ORG"}, {"id": 23, "orth": "from", "tag": "IN", "head": -4, "dep": "prep", "ner": "O"}, {"id": 24, "orth": "1961", "tag": "CD", "head": -1, "dep": "pobj", "ner": "U-DATE"}, {"id": 25, "orth": "until", "tag": "IN", "head": -6, "dep": "prep", "ner": "O"}, {"id": 26, "orth": "his", "tag": "PRP$", "head": 1, "dep": "poss", "ner": "O"}, {"id": 27, "orth": "death", "tag": "NN", "head": -2, "dep": "pobj", "ner": "O"}, {"id": 28, "orth": "in", "tag": "IN", "head": -1, "dep": "prep", "ner": "O"}, {"id": 29, "orth": "1999", "tag": "CD", "head": -1, "dep": "pobj", "ner": "U-DATE"}, {"id": 30, "orth": ".", "tag": ".", "head": -11, "dep": "punct", "ner": "O"}, {"id": 31, "orth": "\n", "tag": "_SP", "head": -1, "dep": "", "ner": "O"}], "brackets": []}, {"tokens": [{"id": 32, "orth": "He", "tag": "PRP", "head": 1, "dep": "nsubj", "ner": "O"}, {"id": 33, "orth": "was", "tag": "VBD", "head": 0, "dep": "ROOT", "ner": "O"}, {"id": 34, "orth": "a", "tag": "DT", "head": 1, "dep": "det", "ner": "O"}, {"id": 35, "orth": "member", "tag": "NN", "head": -2, "dep": "attr", "ner": "O"}, {"id": 36, "orth": "of", "tag": "IN", "head": -1, "dep": "prep", "ner": "O"}, {"id": 37, "orth": "the", "tag": "DT", "head": 2, "dep": "det", "ner": "B-DATE"}, {"id": 38, "orth": "Alaouite", "tag": "NNP", "head": 1, "dep": "compound", "ner": "I-DATE"}, {"id": 39, "orth": "dynasty", "tag": "NN", "head": -3, "dep": "pobj", "ner": "L-DATE"}, {"id": 40, "orth": ".", "tag": ".", "head": -7, "dep": "punct", "ner": "O"}, {"id": 41, "orth": "\n", "tag": "_SP", "head": -1, "dep": "", "ner": "O"}], "brackets": []}, {"tokens": [{"id": 42, "orth": "He", "tag": "PRP", "head": 1, "dep": "nsubj", "ner": "O"}, {"id": 43, "orth": "was", "tag": "VBD", "head": 0, "dep": "ROOT", "ner": "O"}, {"id": 44, "orth": "the", "tag": "DT", "head": 2, "dep": "det", "ner": "O"}, {"id": 45, "orth": "eldest", "tag": "JJS", "head": 1, "dep": "amod", "ner": "O"}, {"id": 46, "orth": "son", "tag": "NN", "head": -3, "dep": "attr", "ner": "O"}, {"id": 47, "orth": "of", "tag": "IN", "head": -1, "dep": "prep", "ner": "O"}, {"id": 48, "orth": "Mohammed", "tag": "NNP", "head": 1, "dep": "compound", "ner": "B-PERSON"}, {"id": 49, "orth": "V", "tag": "NNP", "head": -2, "dep": "pobj", "ner": "L-PERSON"}, {"id": 50, "orth": ",", "tag": ",", "head": -1, "dep": "punct", "ner": "O"}, {"id": 51, "orth": "Sultan", "tag": "NNP", "head": -2, "dep": "appos", "ner": "U-GPE"}, {"id": 52, "orth": ",", "tag": ",", "head": -6, "dep": "punct", "ner": "O"}, {"id": 53, "orth": "then", "tag": "RB", "head": -10, "dep": "advmod", "ner": "O"}, {"id": 54, "orth": "King", "tag": "NNP", "head": -11, "dep": "attr", "ner": "B-ORG"}, {"id": 55, "orth": "of", "tag": "IN", "head": -1, "dep": "prep", "ner": "I-ORG"}, {"id": 56, "orth": "Morocco", "tag": "NNP", "head": -1, "dep": "pobj", "ner": "L-ORG"}, {"id": 57, "orth": ",", "tag": ",", "head": -14, "dep": "punct", "ner": "O"}, {"id": 58, "orth": "and", "tag": "CC", "head": -15, "dep": "cc", "ner": "O"}, {"id": 59, "orth": "his", "tag": "PRP$", "head": 2, "dep": "poss", "ner": "O"}, {"id": 60, "orth": "second", "tag": "JJ", "head": 1, "dep": "amod", "ner": "U-ORDINAL"}, {"id": 61, "orth": "wife", "tag": "NN", "head": -18, "dep": "conj", "ner": "O"}, {"id": 62, "orth": ",", "tag": ",", "head": -1, "dep": "punct", "ner": "O"}, {"id": 63, "orth": "Lalla", "tag": "NNP", "head": 1, "dep": "compound", "ner": "B-LAW"}, {"id": 64, "orth": "Abla", "tag": "NNP", "head": 2, "dep": "compound", "ner": "I-LAW"}, {"id": 65, "orth": "bint", "tag": "NN", "head": 1, "dep": "compound", "ner": "I-LAW"}, {"id": 66, "orth": "Tahar", "tag": "NNP", "head": -5, "dep": "appos", "ner": "L-LAW"}, {"id": 67, "orth": ".", "tag": ".", "head": -24, "dep": "punct", "ner": "O"}, {"id": 68, "orth": "\n", "tag": "_SP", "head": -1, "dep": "", "ner": "O"}], "brackets": []}, {"tokens": [{"id": 69, "orth": "Hassan", "tag": "NNP", "head": 2, "dep": "nsubjpass", "ner": "U-PERSON"}, {"id": 70, "orth": "was", "tag": "VBD", "head": 1, "dep": "auxpass", "ner": "O"}, {"id": 71, "orth": "known", "tag": "VBN", "head": 0, "dep": "ROOT", "ner": "O"}, {"id": 72, "orth": "to", "tag": "TO", "head": 1, "dep": "aux", "ner": "O"}, {"id": 73, "orth": "be", "tag": "VB", "head": -2, "dep": "xcomp", "ner": "O"}, {"id": 74, "orth": "one", "tag": "CD", "head": -1, "dep": "attr", "ner": "O"}, {"id": 75, "orth": "of", "tag": "IN", "head": -1, "dep": "prep", "ner": "O"}, {"id": 76, "orth": "the", "tag": "DT", "head": 3, "dep": "det", "ner": "O"}, {"id": 77, "orth": "most", "tag": "RBS", "head": 1, "dep": "advmod", "ner": "O"}, {"id": 78, "orth": "severe", "tag": "JJ", "head": 1, "dep": "amod", "ner": "O"}, {"id": 79, "orth": "rulers", "tag": "NNS", "head": -4, "dep": "pobj", "ner": "O"}, {"id": 80, "orth": "of", "tag": "IN", "head": -1, "dep": "prep", "ner": "O"}, {"id": 81, "orth": "Morocco", "tag": "NNP", "head": -1, "dep": "pobj", "ner": "U-GPE"}, {"id": 82, "orth": ",", "tag": ",", "head": -11, "dep": "punct", "ner": "O"}, {"id": 83, "orth": "widely", "tag": "RB", "head": 1, "dep": "advmod", "ner": "O"}, {"id": 84, "orth": "accused", "tag": "VBN", "head": -13, "dep": "advcl", "ner": "O"}, {"id": 85, "orth": "of", "tag": "IN", "head": -1, "dep": "prep", "ner": "O"}, {"id": 86, "orth": "authoritarian", "tag": "JJ", "head": 1, "dep": "amod", "ner": "O"}, {"id": 87, "orth": "practices", "tag": "NNS", "head": -2, "dep": "pobj", "ner": "O"}, {"id": 88, "orth": "and", "tag": "CC", "head": -4, "dep": "cc", "ner": "O"}, {"id": 89, "orth": "of", "tag": "IN", "head": -5, "dep": "conj", "ner": "O"}, {"id": 90, "orth": "being", "tag": "VBG", "head": -1, "dep": "pcomp", "ner": "O"}, {"id": 91, "orth": "an", "tag": "DT", "head": 1, "dep": "det", "ner": "O"}, {"id": 92, "orth": "autocrat", "tag": "NN", "head": -2, "dep": "attr", "ner": "O"}, {"id": 93, "orth": "and", "tag": "CC", "head": -1, "dep": "cc", "ner": "O"}, {"id": 94, "orth": "a", "tag": "DT", "head": 1, "dep": "det", "ner": "O"}, {"id": 95, "orth": "dictator", "tag": "NN", "head": -3, "dep": "conj", "ner": "O"}, {"id": 96, "orth": ",", "tag": ",", "head": -7, "dep": "punct", "ner": "O"}, {"id": 97, "orth": "particularly", "tag": "RB", "head": 1, "dep": "advmod", "ner": "O"}, {"id": 98, "orth": "during", "tag": "IN", "head": -9, "dep": "conj", "ner": "O"}, {"id": 99, "orth": "the", "tag": "DT", "head": 1, "dep": "det", "ner": "B-EVENT"}, {"id": 100, "orth": "Years", "tag": "NNS", "head": -2, "dep": "pobj", "ner": "I-EVENT"}, {"id": 101, "orth": "of", "tag": "IN", "head": -1, "dep": "prep", "ner": "I-EVENT"}, {"id": 102, "orth": "Lead", "tag": "NNP", "head": -1, "dep": "pobj", "ner": "L-EVENT"}, {"id": 103, "orth": ".", "tag": ".", "head": -32, "dep": "punct", "ner": "O"}, {"id": 104, "orth": "\n", "tag": "_SP", "head": -1, "dep": "", "ner": "O"}], "brackets": []}], "cats": []}]}]
