[
{"id": 0, "paragraphs": [{"raw": "Arnold R\u00fc\u00fctel served as the last Chairman of the Presidium of the Supreme Soviet of the Estonian SSR from April 8, 1983, to March 29, 1990, Chairman of the Supreme Soviet of the Estonian SSR from March 29, 1990, to October 6, 1992, and was the third President of Estonia from October 8, 2001, to October 9, 2006.\nHe was the second President since Estonia regained independence in 1991.\nR\u00fc\u00fctel also served as one of fifteen Deputy Chairmen of the Supreme Soviet of the USSR.\n", "sentences": [{"tokens": [{"id": 0, "orth": "Arnold", "tag": "NNP", "head": 1, "dep": "compound", "ner": "B-PERSON"}, {"id": 1, "orth": "R\u00fc\u00fctel", "tag": "NNP", "head": 1, "dep": "nsubj", "ner": "L-PERSON"}, {"id": 2, "orth": "served", "tag": "VBD", "head": 0, "dep": "ROOT", "ner": "O"}, {"id": 3, "orth": "as", "tag": "IN", "head": -1, "dep": "prep", "ner": "O"}, {"id": 4, "orth": "the", "tag": "DT", "head": 2, "dep": "det", "ner": "O"}, {"id": 5, "orth": "last", "tag": "JJ", "head": 1, "dep": "amod", "ner": "O"}, {"id": 6, "orth": "Chairman", "tag": "NN", "head": -3, "dep": "pobj", "ner": "O"}, {"id": 7, "orth": "of", "tag": "IN", "head": -1, "dep": "prep", "ner": "O"}, {"id": 8, "orth": "the", "tag": "DT", "head": 1, "dep": "det", "ner": "B-ORG"}, {"id": 9, "orth": "Presidium", "tag": "NNP", "head": -2, "dep": "pobj", "ner": "I-ORG"}, {"id": 10, "orth": "of", "tag": "IN", "head": -1, "dep": "prep", "ner": "I-ORG"}, {"id": 11, "orth": "the", "tag": "DT", "head": 2, "dep": "det", "ner": "I-ORG"}, {"id": 12, "orth": "Supreme", "tag": "NNP", "head": 1, "dep": "compound", "ner": "I-ORG"}, {"id": 13, "orth": "Soviet", "tag": "NNP", "head": -3, "dep": "pobj", "ner": "L-ORG"}, {"id": 14, "orth": "of", "tag": "IN", "head": -1, "dep": "prep", "ner": "O"}, {"id": 15, "orth": "the", "tag": "DT", "head": 2, "dep": "det", "ner": "O"}, {"id": 16, "orth": "Estonian", "tag": "NNP", "head": 1, "dep": "compound", "ner": "O"}, {"id": 17, "orth": "SSR", "tag": "NNP", "head": -3, "dep": "pobj", "ner": "O"}, {"id": 18, "orth": "from", "tag": "IN", "head": -16, "dep": "prep", "ner": "O"}, {"id": 19, "orth": "April", "tag": "NNP", "head": -1, "dep": "pobj", "ner": "B-DATE"}, {"id": 20, "orth": "8", "tag": "CD", "head": -1, "dep": "nummod", "ner": "I-DATE"}, {"id": 21, "orth": ",", "tag": ",", "head": -2, "dep": "punct", "ner": "I-DATE"}, {"id": 22, "orth": "1983", "tag": "CD", "head": -3, "dep": "npadvmod", "ner": "I-DATE"}, {"id": 23, "orth": ",", "tag": ",", "head": -21, "dep": "punct", "ner": "I-DATE"}, {"id": 24, "orth": "to", "tag": "IN", "head": -22, "dep": "prep", "ner": "I-DATE"}, {"id": 25, "orth": "March", "tag": "NNP", "head": -1, "dep": "pobj", "ner": "I-DATE"}, {"id": 26, "orth": "29", "tag": "CD", "head": -1, "dep": "nummod", "ner": "I-DATE"}, {"id": 27, "orth": ",", "tag": ",", "head": -2, "dep": "punct", "ner": "I-DATE"}, {"id": 28, "orth": "1990", "tag": "CD", "head": -3, "dep": "nummod", "ner": "L-DATE"}, {"id": 29, "orth": ",", "tag": ",", "head": -4, "dep": "punct", "ner": "O"}, {"id": 30, "orth": "Chairman", "tag": "NNP", "head": -5, "dep": "appos", "ner": "O"}, {"id": 31, "orth": "of", "tag": "IN", "head": -1, "dep": "prep", "ner": "O"}, {"id": 32, "orth": "the", "tag": "DT", "head": 2, "dep": "det", "ner": "B-ORG"}, {"id": 33, "orth": "Supreme", "tag": "NNP", "head": 1, "dep": "compound", "ner": "I-ORG"}, {"id": 34, "orth": "Soviet", "tag": "NNP", "head": -3, "dep": "pobj", "ner": "L-ORG"}, {"id": 35, "orth": "of", "tag": "IN", "head": -1, "dep": "prep", "ner": "O"}, {"id": 36, "orth": "the", "tag": "DT", "head": 2, "dep": "det", "ner": "O"}, {"id": 37, "orth": "Estonian", "tag": "NNP", "head": 1, "dep": "compound", "ner": "O"}, {"id": 38, "orth": "SSR", "tag": "NNP", "head": -3, "dep": "pobj", "ner": "O"}, {"id": 39, "orth": "from", "tag": "IN", "head": -37, "dep": "prep", "ner": "O"}, {"id": 40, "orth": "March", "tag": "NNP", "head": -1, "dep": "pobj", "ner": "B-DATE"}, {"id": 41, "orth": "29", "tag": "CD", "head": -1, "dep": "nummod", "ner": "I-DATE"}, {"id": 42, "orth": ",", "tag": ",", "head": -2, "dep": "punct", "ner": "I-DATE"}, {"id": 43, "orth": "1990", "tag": "CD", "head": -3, "dep": "nummod", "ner": "L-DATE"}, {"id": 44, "orth": ",", "tag": ",", "head": -42, "dep": "punct", "ner": "O"}, {"id": 45, "orth": "to", "tag": "IN", "head": -43, "dep": "prep", "ner": "O"}, {"id": 46, "orth": "October", "tag": "NNP", "head": -1, "dep": "pobj", "ner": "B-DATE"}, {"id": 47, "orth": "6", "tag": "CD", "head": -1, "dep": "nummod", "ner": "I-DATE"}, {"id": 48, "orth": ",", "tag": ",", "head": -2, "dep": "punct", "ner": "I-DATE"}, {"id": 49, "orth": "1992", "tag": "CD", "head": -3, "dep": "nummod", "ner": "L-DATE"}, {"id": 50, "orth": ",", "tag": ",", "head": -48, "dep": "punct", "ner": "O"}, {"id": 51, "orth": "and", "tag": "CC", "head": -49, "dep": "cc", "ner": "O"}, {"id": 52, "orth": "was", "tag": "VBD", "head": -50, "dep": "conj", "ner": "O"}, {"id": 53, "orth": "the", "tag": "DT", "head": 2, "dep": "det", "ner": "O"}, {"id": 54, "orth": "third", "tag": "JJ", "head": 1, "dep": "amod", "ner": "U-ORDINAL"}, {"id": 55, "orth": "President", "tag": "NNP", "head": -3, "dep": "attr", "ner": "O"}, {"id": 56, "orth": "of", "tag": "IN", "head": -1, "dep": "prep", "ner": "O"}, {"id": 57, "orth": "Estonia", "tag": "NNP", "head": -1, "dep": "pobj", "ner": "U-GPE"}, {"id": 58, "orth": "from", "tag": "IN", "head": -6, "dep": "prep", "ner": "O"}, {"id": 59, "orth": "October", "tag": "NNP", "head": -1, "dep": "pobj", "ner": "B-DATE"}, {"id": 60, "orth": "8", "tag": "CD", "head": -1, "dep": "nummod", "ner": "I-DATE"}, {"id": 61, "orth": ",", "tag": ",", "head": -2, "dep": "punct", "ner": "I-DATE"}, {"id": 62, "orth": "2001", "tag": "CD", "head": -3, "dep": "appos", "ner": "L-DATE"}, {"id": 63, "orth": ",", "tag": ",", "head": -11, "dep": "punct", "ner": "O"}, {"id": 64, "orth": "to", "tag": "IN", "head": -12, "dep": "prep", "ner": "O"}, {"id": 65, "orth": "October", "tag": "NNP", "head": -1, "dep": "pobj", "ner": "B-DATE"}, {"id": 66, "orth": "9", "tag": "CD", "head": -1, "dep": "nummod", "ner": "I-DATE"}, {"id": 67, "orth": ",", "tag": ",", "head": -2, "dep": "punct", "ner": "I-DATE"}, {"id": 68, "orth": "2006", "tag": "CD", "head": -3, "dep": "nummod", "ner": "L-DATE"}, {"id": 69, "orth": ".", "tag": ".", "head": -67, "dep": "punct", "ner": "O"}, {"id": 70, "orth": "\n", "tag": "_SP", "head": -1, "dep": "", "ner": "O"}], "brackets": []}, {"tokens": [{"id": 71, "orth": "He", "tag": "PRP", "head": 1, "dep": "nsubj", "ner": "O"}, {"id": 72, "orth": "was", "tag": "VBD", "head": 0, "dep": "ROOT", "ner": "O"}, {"id": 73, "orth": "the", "tag": "DT", "head": 2, "dep": "det", "ner": "O"}, {"id": 74, "orth": "second", "tag": "JJ", "head": 1, "dep": "amod", "ner": "U-ORDINAL"}, {"id": 75, "orth": "President", "tag": "NNP", "head": -3, "dep": "attr", "ner": "O"}, {"id": 76, "orth": "since", "tag": "IN", "head": 2, "dep": "mark", "ner": "O"}, {"id": 77, "orth": "Estonia", "tag": "NNP", "head": 1, "dep": "nsubj", "ner": "U-GPE"}, {"id": 78, "orth": "regained", "tag": "VBD", "head": -6, "dep": "advcl", "ner": "O"}, {"id": 79, "orth": "independence", "tag": "NN", "head": -1, "dep": "dobj", "ner": "O"}, {"id": 80, "orth": "in", "tag": "IN", "head": -2, "dep": "prep", "ner": "O"}, {"id": 81, "orth": "1991", "tag": "CD", "head": -1, "dep": "pobj", "ner": "U-DATE"}, {"id": 82, "orth": ".", "tag": ".", "head": -10, "dep": "punct", "ner": "O"}, {"id": 83, "orth": "\n", "tag": "_SP", "head": -1, "dep": "", "ner": "O"}], "brackets": []}, {"tokens": [{"id": 84, "orth": "R\u00fc\u00fctel", "tag": "NNP", "head": 2, "dep": "nsubj", "ner": "U-PERSON"}, {"id": 85, "orth": "also", "tag": "RB", "head": 1, "dep": "advmod", "ner": "O"}, {"id": 86, "orth": "served", "tag": "VBD", "head": 0, "dep": "ROOT", "ner": "O"}, {"id": 87, "orth": "as", "tag": "IN", "head": -1, "dep": "prep", "ner": "O"}, {"id": 88, "orth": "one", "tag": "CD", "head": -1, "dep": "pobj", "ner": "U-CARDINAL"}, {"id": 89, "orth": "of", "tag": "IN", "head": -1, "dep": "prep", "ner": "O"}, {"id": 90, "orth": "fifteen", "tag": "CD", "head": 2, "dep": "nummod", "ner": "U-CARDINAL"}, {"id": 91, "orth": "Deputy", "tag": "NNP", "head": 1, "dep": "compound", "ner": "O"}, {"id": 92, "orth": "Chairmen", "tag": "NNPS", "head": -3, "dep": "pobj", "ner": "O"}, {"id": 93, "orth": "of", "tag": "IN", "head": -1, "dep": "prep", "ner": "O"}, {"id": 94, "orth": "the", "tag": "DT", "head": 2, "dep": "det", "ner": "B-ORG"}, {"id": 95, "orth": "Supreme", "tag": "NNP", "head": 1, "dep": "compound", "ner": "I-ORG"}, {"id": 96, "orth": "Soviet", "tag": "NNP", "head": -3, "dep": "pobj", "ner": "L-ORG"}, {"id": 97, "orth": "of", "tag": "IN", "head": -1, "dep": "prep", "ner": "O"}, {"id": 98, "orth": "the", "tag": "DT", "head": 1, "dep": "det", "ner": "O"}, {"id": 99, "orth": "USSR", "tag": "NNP", "head": -2, "dep": "pobj", "ner": "U-GPE"}, {"id": 100, "orth": ".", "tag": ".", "head": -14, "dep": "punct", "ner": "O"}, {"id": 101, "orth": "\n", "tag": "_SP", "head": -1, "dep": "", "ner": "O"}], "brackets": []}], "cats": []}]}]
