[
{"id": 0, "paragraphs": [{"raw": "Prince Makhosini Jaheso Dlamini was Prime Ministerf Eswatini from 16 May 1967 to 31 March 1976.\n", "sentences": [{"tokens": [{"id": 0, "orth": "Prince", "tag": "NNP", "head": 1, "dep": "compound", "ner": "B-PERSON"}, {"id": 1, "orth": "Makhosini", "tag": "NNP", "head": 2, "dep": "compound", "ner": "B-PERSON"}, {"id": 2, "orth": "Jaheso", "tag": "NNP", "head": 1, "dep": "compound", "ner": "B-PERSON"}, {"id": 3, "orth": "Dlamini", "tag": "NNP", "head": 1, "dep": "nsubj", "ner": "L-PERSON"}, {"id": 4, "orth": "was", "tag": "VBD", "head": 0, "dep": "ROOT", "ner": "O"}, {"id": 5, "orth": "Prime", "tag": "NNP", "head": 2, "dep": "compound", "ner": "O"}, {"id": 6, "orth": "Ministerf", "tag": "NNP", "head": 1, "dep": "compound", "ner": "O"}, {"id": 7, "orth": "Eswatini", "tag": "NNP", "head": -3, "dep": "attr", "ner": "O"}, {"id": 8, "orth": "from", "tag": "IN", "head": -4, "dep": "prep", "ner": "O"}, {"id": 9, "orth": "16", "tag": "CD", "head": 1, "dep": "nummod", "ner": "U-CARDINAL"}, {"id": 10, "orth": "May", "tag": "NNP", "head": -2, "dep": "pobj", "ner": "B-DATE"}, {"id": 11, "orth": "1967", "tag": "CD", "head": -1, "dep": "nummod", "ner": "L-DATE"}, {"id": 12, "orth": "to", "tag": "IN", "head": -4, "dep": "prep", "ner": "O"}, {"id": 13, "orth": "31", "tag": "CD", "head": 1, "dep": "nummod", "ner": "U-CARDINAL"}, {"id": 14, "orth": "March", "tag": "NNP", "head": -2, "dep": "pobj", "ner": "B-DATE"}, {"id": 15, "orth": "1976", "tag": "CD", "head": -1, "dep": "nummod", "ner": "L-DATE"}, {"id": 16, "orth": ".", "tag": ".", "head": -12, "dep": "punct", "ner": "O"}, {"id": 17, "orth": "\n", "tag": "_SP", "head": -1, "dep": "", "ner": "O"}], "brackets": []}], "cats": []}]}]
